<?xml version="1.0" encoding="UTF-8"?>
<AudioParam version="1.1">
  <ParamTree>
    <Param path="" param_id="0"/>
    <Param path="Default,CamRecNormal,4-pole HS" param_id="1"/>
    <Param path="Default,SndRecNormal,Handset" param_id="2"/>
    <Param path="Default,SndRecNormal,4-pole HS" param_id="3"/>
    <Param path="Default,CamRecNormal,Handset" param_id="4"/>
    <Param path="Default,SndRecNormal,BT earphone" param_id="5"/>
    <Param path="Default,CamRecNormal,BT earphone" param_id="6"/>
    <Param path="Default,VR,4-pole HS" param_id="7"/>
    <Param path="Default,VR,Handset" param_id="8"/>
    <Param path="Default,VR,BT earphone" param_id="9"/>
    <Param path="Default,VR,USB" param_id="10"/>
    <Param path="Default,VoicePerformance,4-pole HS" param_id="11"/>
    <Param path="Default,VoicePerformance,Handset" param_id="12"/>
    <Param path="Default,VoicePerformance,BT earphone" param_id="13"/>
    <Param path="Default,VoicePerformance,USB" param_id="14"/>
  </ParamTree>
  <ParamUnitPool>
    <ParamUnit param_id="0">
      <Param name="sph_in_fir1" value="32767,0,0,0,0,0,0,0,0,0,0,0,0,0,0,0,0,0,0,0,0,0,0,0,0,0,0,0,0,0,0,0,0,0,0,0,0,0,0,0,0,0,0,0,0,0,0,0,0,0,0,0,0,0,0,0,0,0,0,0,0,0,0,0,0,0,0,0,0,0,0,0,0,0,0,0,0,0,0,0,0,0,0,0,0,0,0,0,0,0"/>
      <Param name="sph_in_fir1_eq_freq" value="100.000000,500.000000,1000.000000,2000.000000,3000.000000,4000.000000,5000.000000,5300.000000,6000.000000,7500.000000"/>
      <Param name="sph_in_fir1_eq_mag" value="1.000000,1.000000,4.000000,4.000000,5.000000,3.000000,2.000000,4.000000,8.000000,12.000000"/>
      <Param name="sph_in_fir2" value="32767,0,0,0,0,0,0,0,0,0,0,0,0,0,0,0,0,0,0,0,0,0,0,0,0,0,0,0,0,0,0,0,0,0,0,0,0,0,0,0,0,0,0,0,0,0,0,0,0,0,0,0,0,0,0,0,0,0,0,0,0,0,0,0,0,0,0,0,0,0,0,0,0,0,0,0,0,0,0,0,0,0,0,0,0,0,0,0,0,0"/>
      <Param name="sph_in_fir2_eq_freq" value="100.000000,500.000000,1000.000000,2000.000000,3000.000000,4000.000000,5000.000000,5300.000000,6000.000000,7500.000000"/>
      <Param name="sph_in_fir2_eq_mag" value="1.000000,1.000000,4.000000,4.000000,5.000000,3.000000,2.000000,4.000000,8.000000,12.000000"/>
      <Param name="sph_in_parameter" value="0.000000,0.000000"/>
    </ParamUnit>
    <ParamUnit param_id="1">
      <Param name="sph_in_fir1" value="-344,-188,-289,-257,-357,-259,-277,-155,-160,-42,-19,79,64,69,41,79,189,184,176,319,281,226,211,340,334,-184,198,-285,138,-516,32,-938,-500,-2105,-1755,-3809,-2951,-4930,-2483,-3459,2334,2493,11832,7312,32767,32767,7312,11832,2493,2334,-3459,-2483,-4930,-2951,-3809,-1755,-2105,-500,-938,32,-516,138,-285,198,-184,334,340,211,226,281,319,176,184,189,79,41,69,64,79,-19,-42,-160,-155,-277,-259,-357,-257,-289,-188,-344"/>
      <Param name="sph_in_fir1_eq_freq" value="100.000000,198.672310,300.000000,585.000000,1000.000000,1540.500601,2087.489513,2992.431514,4194.000000,5000.000000,6012.416521,8056.084119,24000.000000"/>
      <Param name="sph_in_fir1_eq_mag" value="-8.877551,-3.367347,0.000000,0.000000,0.000000,3.673469,4.285714,3.673469,0.000000,-4.000000,-6.734694,-8.877551,-10.000000"/>
      <Param name="sph_in_fir2" value="32767,0,0,0,0,0,0,0,0,0,0,0,0,0,0,0,0,0,0,0,0,0,0,0,0,0,0,0,0,0,0,0,0,0,0,0,0,0,0,0,0,0,0,0,0,0,0,0,0,0,0,0,0,0,0,0,0,0,0,0,0,0,0,0,0,0,0,0,0,0,0,0,0,0,0,0,0,0,0,0,0,0,0,0,0,0,0,0,0,0"/>
      <Param name="sph_in_fir2_eq_freq" value="100.000000,500.000000,1000.000000,2000.000000,3000.000000,4000.000000,5000.000000,5300.000000,6000.000000,7500.000000"/>
      <Param name="sph_in_fir2_eq_mag" value="1.000000,1.000000,4.000000,4.000000,5.000000,3.000000,2.000000,4.000000,8.000000,12.000000"/>
      <Param name="sph_in_parameter" value="0.000000,0.000000"/>
    </ParamUnit>
    <ParamUnit param_id="2">
      <Param name="sph_in_fir1" value="-157,-43,-95,-110,-188,-184,-218,-208,-214,-183,-128,-93,-44,-82,-27,-33,163,141,254,236,323,141,249,102,220,-273,197,-271,316,-277,408,-578,-104,-1793,-1443,-3566,-2683,-4697,-2253,-3371,2173,1926,10996,6338,32767,32767,6338,10996,1926,2173,-3371,-2253,-4697,-2683,-3566,-1443,-1793,-104,-578,408,-277,316,-271,197,-273,220,102,249,141,323,236,254,141,163,-33,-27,-82,-44,-93,-128,-183,-214,-208,-218,-184,-188,-110,-95,-43,-157"/>
      <Param name="sph_in_fir1_eq_freq" value="100.000000,194.250590,300.000000,585.244168,1000.000000,1506.214684,2111.114554,3311.400397,4194.200061,5000.000000,6000.000000,8000.000000,24000.000000"/>
      <Param name="sph_in_fir1_eq_mag" value="-8.265306,-3.367347,0.000000,0.000000,0.000000,2.755102,3.979592,3.061224,0.000000,-4.000000,-6.000000,-8.000000,-10.000000"/>
      <Param name="sph_in_fir2" value="-158,-43,-96,-110,-188,-183,-218,-207,-214,-183,-128,-92,-44,-81,-27,-32,163,142,255,237,323,142,249,103,220,-273,197,-272,314,-279,405,-580,-106,-1794,-1444,-3566,-2682,-4695,-2251,-3369,2175,1928,10997,6339,32767,32767,6339,10997,1928,2175,-3369,-2251,-4695,-2682,-3566,-1444,-1794,-106,-580,405,-279,314,-272,197,-273,220,103,249,142,323,237,255,142,163,-32,-27,-81,-44,-92,-128,-183,-214,-207,-218,-183,-188,-110,-96,-43,-158"/>
      <Param name="sph_in_fir2_eq_freq" value="100.000000,194.000000,300.000000,585.000000,1000.000000,1506.000000,2111.000000,3311.000000,4194.000000,5000.000000,6000.000000,8000.000000,24000.000000"/>
      <Param name="sph_in_fir2_eq_mag" value="-8.270000,-3.370000,0.000000,0.000000,0.000000,2.760000,3.980000,3.060000,0.000000,-4.000000,-6.000000,-8.000000,-10.000000"/>
      <Param name="sph_in_parameter" value="0.000000,0.000000"/>
    </ParamUnit>
    <ParamUnit param_id="3">
      <Param name="sph_in_fir1" value="-140,-76,-131,-154,-208,-197,-191,-158,-115,-78,-11,-17,9,-85,-46,-97,111,104,330,363,583,434,602,346,421,-264,21,-666,-169,-852,-98,-1002,-268,-1718,-1012,-2932,-1825,-3871,-1434,-2836,2534,1811,10807,5701,32767,32767,5701,10807,1811,2534,-2836,-1434,-3871,-1825,-2932,-1012,-1718,-268,-1002,-98,-852,-169,-666,21,-264,421,346,602,434,583,363,330,104,111,-97,-46,-85,9,-17,-11,-78,-115,-158,-191,-197,-208,-154,-131,-76,-140"/>
      <Param name="sph_in_fir1_eq_freq" value="100.000000,200.000000,300.000000,585.000000,1000.000000,1489.358951,2041.029621,3026.298183,4194.000000,5000.000000,6000.000000,8000.000000,24000.000000"/>
      <Param name="sph_in_fir1_eq_mag" value="-7.959184,-2.000000,0.000000,0.000000,0.000000,2.755102,3.673469,1.836735,0.000000,-4.000000,-6.000000,-8.000000,-10.000000"/>
      <Param name="sph_in_fir2" value="32767,0,0,0,0,0,0,0,0,0,0,0,0,0,0,0,0,0,0,0,0,0,0,0,0,0,0,0,0,0,0,0,0,0,0,0,0,0,0,0,0,0,0,0,0,0,0,0,0,0,0,0,0,0,0,0,0,0,0,0,0,0,0,0,0,0,0,0,0,0,0,0,0,0,0,0,0,0,0,0,0,0,0,0,0,0,0,0,0,0"/>
      <Param name="sph_in_fir2_eq_freq" value="100.000000,500.000000,1000.000000,2000.000000,3000.000000,4000.000000,5000.000000,5300.000000,6000.000000,7500.000000"/>
      <Param name="sph_in_fir2_eq_mag" value="1.000000,1.000000,4.000000,4.000000,5.000000,3.000000,2.000000,4.000000,8.000000,12.000000"/>
      <Param name="sph_in_parameter" value="0.000000,0.000000"/>
    </ParamUnit>
    <ParamUnit param_id="4">
      <Param name="sph_in_fir1" value="-158,-43,-96,-110,-188,-183,-218,-207,-214,-183,-128,-92,-44,-81,-27,-32,163,142,255,237,323,142,249,103,220,-273,197,-272,314,-279,405,-580,-106,-1794,-1444,-3566,-2682,-4695,-2251,-3369,2175,1928,10997,6339,32767,32767,6339,10997,1928,2175,-3369,-2251,-4695,-2682,-3566,-1444,-1794,-106,-580,405,-279,314,-272,197,-273,220,103,249,142,323,237,255,142,163,-32,-27,-81,-44,-92,-128,-183,-214,-207,-218,-183,-188,-110,-96,-43,-158"/>
      <Param name="sph_in_fir1_eq_freq" value="100.000000,194.000000,300.000000,585.000000,1000.000000,1506.000000,2111.000000,3311.000000,4194.000000,5000.000000,6000.000000,8000.000000,24000.000000"/>
      <Param name="sph_in_fir1_eq_mag" value="-8.270000,-3.370000,0.000000,0.000000,0.000000,2.760000,3.980000,3.060000,0.000000,-4.000000,-6.000000,-8.000000,-10.000000"/>
      <Param name="sph_in_fir2" value="-158,-43,-96,-110,-188,-183,-218,-207,-214,-183,-128,-92,-44,-81,-27,-32,163,142,255,237,323,142,249,103,220,-273,197,-272,314,-279,405,-580,-106,-1794,-1444,-3566,-2682,-4695,-2251,-3369,2175,1928,10997,6339,32767,32767,6339,10997,1928,2175,-3369,-2251,-4695,-2682,-3566,-1444,-1794,-106,-580,405,-279,314,-272,197,-273,220,103,249,142,323,237,255,142,163,-32,-27,-81,-44,-92,-128,-183,-214,-207,-218,-183,-188,-110,-96,-43,-158"/>
      <Param name="sph_in_fir2_eq_freq" value="100.000000,194.000000,300.000000,585.000000,1000.000000,1506.000000,2111.000000,3311.000000,4194.000000,5000.000000,6000.000000,8000.000000,24000.000000"/>
      <Param name="sph_in_fir2_eq_mag" value="-8.270000,-3.370000,0.000000,0.000000,0.000000,2.760000,3.980000,3.060000,0.000000,-4.000000,-6.000000,-8.000000,-10.000000"/>
      <Param name="sph_in_parameter" value="0.000000,0.000000"/>
    </ParamUnit>
    <ParamUnit param_id="5">
      <Param name="sph_in_fir1" value="-33,-16,-8,-15,-12,-30,-5,-26,12,-35,9,-59,15,-65,41,-75,55,-111,57,-108,106,-135,115,-186,164,-252,248,-268,289,-397,326,-447,510,-503,589,-790,681,-928,1230,-1100,1538,-2687,1854,-3638,32766,32766,-3638,1854,-2687,1538,-1100,1230,-928,681,-790,589,-503,510,-447,326,-397,289,-268,248,-252,164,-186,115,-135,106,-108,57,-111,55,-75,41,-65,15,-59,9,-35,12,-26,-5,-30,-12,-15,-8,-16,-33"/>
      <Param name="sph_in_fir1_eq_freq" value="100.000000,200.000000,300.000000,585.000000,1000.000000,1500.000000,2000.000000,3000.000000,4194.000000,5000.000000,6000.000000,8000.000000,24000.000000"/>
      <Param name="sph_in_fir1_eq_mag" value="-6.428571,0.000000,0.000000,0.000000,0.000000,0.000000,0.000000,0.000000,0.000000,0.000000,0.000000,0.000000,-7.959184"/>
      <Param name="sph_in_fir2" value="32767,0,0,0,0,0,0,0,0,0,0,0,0,0,0,0,0,0,0,0,0,0,0,0,0,0,0,0,0,0,0,0,0,0,0,0,0,0,0,0,0,0,0,0,0,0,0,0,0,0,0,0,0,0,0,0,0,0,0,0,0,0,0,0,0,0,0,0,0,0,0,0,0,0,0,0,0,0,0,0,0,0,0,0,0,0,0,0,0,0"/>
      <Param name="sph_in_fir2_eq_freq" value="100.000000,500.000000,1000.000000,2000.000000,3000.000000,4000.000000,5000.000000,5300.000000,6000.000000,7500.000000"/>
      <Param name="sph_in_fir2_eq_mag" value="1.000000,1.000000,4.000000,4.000000,5.000000,3.000000,2.000000,4.000000,8.000000,12.000000"/>
      <Param name="sph_in_parameter" value="0.000000,0.000000"/>
    </ParamUnit>
    <ParamUnit param_id="6">
      <Param name="sph_in_fir1" value="-93,-57,-64,-62,-61,-63,-44,-72,-51,-109,-60,-133,-51,-162,-51,-197,-28,-235,-45,-241,0,-310,-2,-342,73,-522,124,-555,220,-662,291,-816,385,-993,567,-1153,890,-1420,1224,-2125,1668,-3416,3468,-5765,32767,32767,-5765,3468,-3416,1668,-2125,1224,-1420,890,-1153,567,-993,385,-816,291,-662,220,-555,124,-522,73,-342,-2,-310,0,-241,-45,-235,-28,-197,-51,-162,-51,-133,-60,-109,-51,-72,-44,-63,-61,-62,-64,-57,-93"/>
      <Param name="sph_in_fir1_eq_freq" value="100.000000,337.170617,1000.000000,2000.000000,3000.000000,4000.000000,5000.000000,5300.000000,6000.000000,24000.000000"/>
      <Param name="sph_in_fir1_eq_mag" value="-5.204082,-0.918367,0.000000,0.000000,0.000000,0.000000,0.000000,0.000000,0.000000,-5.204082"/>
      <Param name="sph_in_fir2" value="32767,0,0,0,0,0,0,0,0,0,0,0,0,0,0,0,0,0,0,0,0,0,0,0,0,0,0,0,0,0,0,0,0,0,0,0,0,0,0,0,0,0,0,0,0,0,0,0,0,0,0,0,0,0,0,0,0,0,0,0,0,0,0,0,0,0,0,0,0,0,0,0,0,0,0,0,0,0,0,0,0,0,0,0,0,0,0,0,0,0"/>
      <Param name="sph_in_fir2_eq_freq" value="100.000000,500.000000,1000.000000,2000.000000,3000.000000,4000.000000,5000.000000,5300.000000,6000.000000,7500.000000"/>
      <Param name="sph_in_fir2_eq_mag" value="1.000000,1.000000,4.000000,4.000000,5.000000,3.000000,2.000000,4.000000,8.000000,12.000000"/>
      <Param name="sph_in_parameter" value="0.000000,0.000000"/>
    </ParamUnit>
    <ParamUnit param_id="7">
      <Param name="sph_in_fir1" value="6,-12,15,-20,26,-32,39,-47,57,-66,78,-91,104,-120,137,-154,176,-200,223,-249,280,-314,354,-402,453,-502,556,-621,691,-767,855,-954,1065,-1196,1349,-1529,1751,-2027,2381,-2860,3544,-4602,6492,-10887,32767,32767,-10887,6492,-4602,3544,-2860,2381,-2027,1751,-1529,1349,-1196,1065,-954,855,-767,691,-621,556,-502,453,-402,354,-314,280,-249,223,-200,176,-154,137,-120,104,-91,78,-66,57,-47,39,-32,26,-20,15,-12,6"/>
      <Param name="sph_in_fir1_eq_freq" value="100.000000,500.000000,1000.000000,2000.000000,3000.000000,4000.000000,6578.835676,10916.575496,16369.534500,24000.000000"/>
      <Param name="sph_in_fir1_eq_mag" value="0.000000,0.000000,0.000000,0.000000,0.000000,0.000000,0.000000,0.000000,0.000000,0.000000"/>
      <Param name="sph_in_fir2" value="32767,0,0,0,0,0,0,0,0,0,0,0,0,0,0,0,0,0,0,0,0,0,0,0,0,0,0,0,0,0,0,0,0,0,0,0,0,0,0,0,0,0,0,0,0,0,0,0,0,0,0,0,0,0,0,0,0,0,0,0,0,0,0,0,0,0,0,0,0,0,0,0,0,0,0,0,0,0,0,0,0,0,0,0,0,0,0,0,0,0"/>
      <Param name="sph_in_fir2_eq_freq" value="100.000000,500.000000,1000.000000,2000.000000,3000.000000,4000.000000,5000.000000,5300.000000,6000.000000,7500.000000"/>
      <Param name="sph_in_fir2_eq_mag" value="1.000000,1.000000,4.000000,4.000000,5.000000,3.000000,2.000000,4.000000,8.000000,12.000000"/>
      <Param name="sph_in_parameter" value="0.000000,0.000000"/>
    </ParamUnit>
    <ParamUnit param_id="8">
      <Param name="sph_in_fir1" value="6,-12,15,-20,26,-32,39,-47,57,-66,78,-91,104,-120,137,-154,176,-200,223,-249,280,-314,354,-402,453,-502,556,-621,691,-767,855,-954,1065,-1196,1349,-1529,1751,-2027,2381,-2860,3544,-4602,6492,-10887,32767,32767,-10887,6492,-4602,3544,-2860,2381,-2027,1751,-1529,1349,-1196,1065,-954,855,-767,691,-621,556,-502,453,-402,354,-314,280,-249,223,-200,176,-154,137,-120,104,-91,78,-66,57,-47,39,-32,26,-20,15,-12,6"/>
      <Param name="sph_in_fir1_eq_freq" value="100.000000,500.000000,1000.000000,2000.000000,3000.000000,4000.000000,6080.461695,11165.069156,15473.866386,24000.000000"/>
      <Param name="sph_in_fir1_eq_mag" value="0.000000,0.000000,0.000000,0.000000,0.000000,0.000000,0.000000,0.000000,0.000000,0.000000"/>
      <Param name="sph_in_fir2" value="32767,0,0,0,0,0,0,0,0,0,0,0,0,0,0,0,0,0,0,0,0,0,0,0,0,0,0,0,0,0,0,0,0,0,0,0,0,0,0,0,0,0,0,0,0,0,0,0,0,0,0,0,0,0,0,0,0,0,0,0,0,0,0,0,0,0,0,0,0,0,0,0,0,0,0,0,0,0,0,0,0,0,0,0,0,0,0,0,0,0"/>
      <Param name="sph_in_fir2_eq_freq" value="100.000000,500.000000,1000.000000,2000.000000,3000.000000,4000.000000,5000.000000,5300.000000,6000.000000,7500.000000"/>
      <Param name="sph_in_fir2_eq_mag" value="1.000000,1.000000,4.000000,4.000000,5.000000,3.000000,2.000000,4.000000,8.000000,12.000000"/>
      <Param name="sph_in_parameter" value="0.000000,0.000000"/>
    </ParamUnit>
    <ParamUnit param_id="9">
      <Param name="sph_in_fir1" value="6,-12,15,-20,26,-32,39,-47,57,-66,78,-91,104,-120,137,-154,176,-200,223,-249,280,-314,354,-402,453,-502,556,-621,691,-767,855,-954,1065,-1196,1349,-1529,1751,-2027,2381,-2860,3544,-4602,6492,-10887,32767,32767,-10887,6492,-4602,3544,-2860,2381,-2027,1751,-1529,1349,-1196,1065,-954,855,-767,691,-621,556,-502,453,-402,354,-314,280,-249,223,-200,176,-154,137,-120,104,-91,78,-66,57,-47,39,-32,26,-20,15,-12,6"/>
      <Param name="sph_in_fir1_eq_freq" value="100.000000,500.000000,1000.000000,2000.000000,3000.000000,4000.000000,6149.276967,9754.644543,12924.057567,24000.000000"/>
      <Param name="sph_in_fir1_eq_mag" value="0.000000,0.000000,0.000000,0.000000,0.000000,0.000000,0.000000,0.000000,0.000000,0.000000"/>
      <Param name="sph_in_fir2" value="32767,0,0,0,0,0,0,0,0,0,0,0,0,0,0,0,0,0,0,0,0,0,0,0,0,0,0,0,0,0,0,0,0,0,0,0,0,0,0,0,0,0,0,0,0,0,0,0,0,0,0,0,0,0,0,0,0,0,0,0,0,0,0,0,0,0,0,0,0,0,0,0,0,0,0,0,0,0,0,0,0,0,0,0,0,0,0,0,0,0"/>
      <Param name="sph_in_fir2_eq_freq" value="100.000000,500.000000,1000.000000,2000.000000,3000.000000,4000.000000,5000.000000,5300.000000,6000.000000,7500.000000"/>
      <Param name="sph_in_fir2_eq_mag" value="1.000000,1.000000,4.000000,4.000000,5.000000,3.000000,2.000000,4.000000,8.000000,12.000000"/>
      <Param name="sph_in_parameter" value="0.000000,0.000000"/>
    </ParamUnit>
    <ParamUnit param_id="10">
      <Param name="sph_in_fir1" value="6,-12,15,-20,26,-32,39,-47,57,-66,78,-91,104,-120,137,-154,176,-200,223,-249,280,-314,354,-402,453,-502,556,-621,691,-767,855,-954,1065,-1196,1349,-1529,1751,-2027,2381,-2860,3544,-4602,6492,-10887,32767,32767,-10887,6492,-4602,3544,-2860,2381,-2027,1751,-1529,1349,-1196,1065,-954,855,-767,691,-621,556,-502,453,-402,354,-314,280,-249,223,-200,176,-154,137,-120,104,-91,78,-66,57,-47,39,-32,26,-20,15,-12,6"/>
      <Param name="sph_in_fir1_eq_freq" value="100.000000,500.000000,1000.000000,2000.000000,3000.000000,4000.000000,5878.602089,8427.019173,11419.219269,24000.000000"/>
      <Param name="sph_in_fir1_eq_mag" value="0.000000,0.000000,0.000000,0.000000,0.000000,0.000000,0.000000,0.000000,0.000000,0.000000"/>
      <Param name="sph_in_fir2" value="32767,0,0,0,0,0,0,0,0,0,0,0,0,0,0,0,0,0,0,0,0,0,0,0,0,0,0,0,0,0,0,0,0,0,0,0,0,0,0,0,0,0,0,0,0,0,0,0,0,0,0,0,0,0,0,0,0,0,0,0,0,0,0,0,0,0,0,0,0,0,0,0,0,0,0,0,0,0,0,0,0,0,0,0,0,0,0,0,0,0"/>
      <Param name="sph_in_fir2_eq_freq" value="100.000000,500.000000,1000.000000,2000.000000,3000.000000,4000.000000,5000.000000,5300.000000,6000.000000,7500.000000"/>
      <Param name="sph_in_fir2_eq_mag" value="1.000000,1.000000,4.000000,4.000000,5.000000,3.000000,2.000000,4.000000,8.000000,12.000000"/>
      <Param name="sph_in_parameter" value="0.000000,0.000000"/>
    </ParamUnit>
    <ParamUnit param_id="11">
      <Param name="sph_in_fir1" value="6,-12,15,-20,26,-32,39,-47,57,-66,78,-91,104,-120,137,-154,176,-200,223,-249,280,-314,354,-402,453,-502,556,-621,691,-767,855,-954,1065,-1196,1349,-1529,1751,-2027,2381,-2860,3544,-4602,6492,-10887,32767,32767,-10887,6492,-4602,3544,-2860,2381,-2027,1751,-1529,1349,-1196,1065,-954,855,-767,691,-621,556,-502,453,-402,354,-314,280,-249,223,-200,176,-154,137,-120,104,-91,78,-66,57,-47,39,-32,26,-20,15,-12,6"/>
      <Param name="sph_in_fir1_eq_freq" value="100.000000,500.000000,1000.000000,2000.000000,3000.000000,4000.000000,5000.000000,8815.033593,13672.136036,24000.000000"/>
      <Param name="sph_in_fir1_eq_mag" value="0.000000,0.000000,0.000000,0.000000,0.000000,0.000000,0.000000,0.000000,0.000000,0.000000"/>
      <Param name="sph_in_fir2" value="32767,0,0,0,0,0,0,0,0,0,0,0,0,0,0,0,0,0,0,0,0,0,0,0,0,0,0,0,0,0,0,0,0,0,0,0,0,0,0,0,0,0,0,0,0,0,0,0,0,0,0,0,0,0,0,0,0,0,0,0,0,0,0,0,0,0,0,0,0,0,0,0,0,0,0,0,0,0,0,0,0,0,0,0,0,0,0,0,0,0"/>
      <Param name="sph_in_fir2_eq_freq" value="100.000000,500.000000,1000.000000,2000.000000,3000.000000,4000.000000,5000.000000,5300.000000,6000.000000,7500.000000"/>
      <Param name="sph_in_fir2_eq_mag" value="1.000000,1.000000,4.000000,4.000000,5.000000,3.000000,2.000000,4.000000,8.000000,12.000000"/>
      <Param name="sph_in_parameter" value="0.000000,0.000000"/>
    </ParamUnit>
    <ParamUnit param_id="12">
      <Param name="sph_in_fir1" value="6,-12,15,-20,26,-32,39,-47,57,-66,78,-91,104,-120,137,-154,176,-200,223,-249,280,-314,354,-402,453,-502,556,-621,691,-767,855,-954,1065,-1196,1349,-1529,1751,-2027,2381,-2860,3544,-4602,6492,-10887,32767,32767,-10887,6492,-4602,3544,-2860,2381,-2027,1751,-1529,1349,-1196,1065,-954,855,-767,691,-621,556,-502,453,-402,354,-314,280,-249,223,-200,176,-154,137,-120,104,-91,78,-66,57,-47,39,-32,26,-20,15,-12,6"/>
      <Param name="sph_in_fir1_eq_freq" value="100.000000,500.000000,1000.000000,2000.000000,3000.000000,4000.000000,6218.871051,9754.644543,14141.610232,24000.000000"/>
      <Param name="sph_in_fir1_eq_mag" value="0.000000,0.000000,0.000000,0.000000,0.000000,0.000000,0.000000,0.000000,0.000000,0.000000"/>
      <Param name="sph_in_fir2" value="32767,0,0,0,0,0,0,0,0,0,0,0,0,0,0,0,0,0,0,0,0,0,0,0,0,0,0,0,0,0,0,0,0,0,0,0,0,0,0,0,0,0,0,0,0,0,0,0,0,0,0,0,0,0,0,0,0,0,0,0,0,0,0,0,0,0,0,0,0,0,0,0,0,0,0,0,0,0,0,0,0,0,0,0,0,0,0,0,0,0"/>
      <Param name="sph_in_fir2_eq_freq" value="100.000000,500.000000,1000.000000,2000.000000,3000.000000,4000.000000,5000.000000,5300.000000,6000.000000,7500.000000"/>
      <Param name="sph_in_fir2_eq_mag" value="1.000000,1.000000,4.000000,4.000000,5.000000,3.000000,2.000000,4.000000,8.000000,12.000000"/>
      <Param name="sph_in_parameter" value="0.000000,0.000000"/>
    </ParamUnit>
    <ParamUnit param_id="13">
      <Param name="sph_in_fir1" value="6,-12,15,-20,26,-32,39,-47,57,-66,78,-91,104,-120,137,-154,176,-200,223,-249,280,-314,354,-402,453,-502,556,-621,691,-767,855,-954,1065,-1196,1349,-1529,1751,-2027,2381,-2860,3544,-4602,6492,-10887,32767,32767,-10887,6492,-4602,3544,-2860,2381,-2027,1751,-1529,1349,-1196,1065,-954,855,-767,691,-621,556,-502,453,-402,354,-314,280,-249,223,-200,176,-154,137,-120,104,-91,78,-66,57,-47,39,-32,26,-20,15,-12,6"/>
      <Param name="sph_in_fir1_eq_freq" value="100.000000,500.000000,1000.000000,2000.000000,3000.000000,4000.000000,6012.416521,7965.930168,11291.429176,24000.000000"/>
      <Param name="sph_in_fir1_eq_mag" value="0.000000,0.000000,0.000000,0.000000,0.000000,0.000000,0.000000,0.000000,0.000000,0.000000"/>
      <Param name="sph_in_fir2" value="32767,0,0,0,0,0,0,0,0,0,0,0,0,0,0,0,0,0,0,0,0,0,0,0,0,0,0,0,0,0,0,0,0,0,0,0,0,0,0,0,0,0,0,0,0,0,0,0,0,0,0,0,0,0,0,0,0,0,0,0,0,0,0,0,0,0,0,0,0,0,0,0,0,0,0,0,0,0,0,0,0,0,0,0,0,0,0,0,0,0"/>
      <Param name="sph_in_fir2_eq_freq" value="100.000000,500.000000,1000.000000,2000.000000,3000.000000,4000.000000,5000.000000,5300.000000,6000.000000,7500.000000"/>
      <Param name="sph_in_fir2_eq_mag" value="1.000000,1.000000,4.000000,4.000000,5.000000,3.000000,2.000000,4.000000,8.000000,12.000000"/>
      <Param name="sph_in_parameter" value="0.000000,0.000000"/>
    </ParamUnit>
    <ParamUnit param_id="14">
      <Param name="sph_in_fir1" value="6,-12,15,-20,26,-32,39,-47,57,-66,78,-91,104,-120,137,-154,176,-200,223,-249,280,-314,354,-402,453,-502,556,-621,691,-767,855,-954,1065,-1196,1349,-1529,1751,-2027,2381,-2860,3544,-4602,6492,-10887,32767,32767,-10887,6492,-4602,3544,-2860,2381,-2027,1751,-1529,1349,-1196,1065,-954,855,-767,691,-621,556,-502,453,-402,354,-314,280,-249,223,-200,176,-154,137,-120,104,-91,78,-66,57,-47,39,-32,26,-20,15,-12,6"/>
      <Param name="sph_in_fir1_eq_freq" value="100.000000,500.000000,1000.000000,2000.000000,3000.000000,4000.000000,5252.899484,7118.057972,12080.193736,24000.000000"/>
      <Param name="sph_in_fir1_eq_mag" value="0.000000,0.000000,0.000000,0.000000,0.000000,0.000000,0.000000,0.000000,0.000000,0.000000"/>
      <Param name="sph_in_fir2" value="32767,0,0,0,0,0,0,0,0,0,0,0,0,0,0,0,0,0,0,0,0,0,0,0,0,0,0,0,0,0,0,0,0,0,0,0,0,0,0,0,0,0,0,0,0,0,0,0,0,0,0,0,0,0,0,0,0,0,0,0,0,0,0,0,0,0,0,0,0,0,0,0,0,0,0,0,0,0,0,0,0,0,0,0,0,0,0,0,0,0"/>
      <Param name="sph_in_fir2_eq_freq" value="100.000000,500.000000,1000.000000,2000.000000,3000.000000,4000.000000,5000.000000,5300.000000,6000.000000,7500.000000"/>
      <Param name="sph_in_fir2_eq_mag" value="1.000000,1.000000,4.000000,4.000000,5.000000,3.000000,2.000000,4.000000,8.000000,12.000000"/>
      <Param name="sph_in_parameter" value="0.000000,0.000000"/>
    </ParamUnit>
  </ParamUnitPool>
</AudioParam>
